{"Company_details": [{"%Chg": "0.76", "Industry": "Finance - Investments", "Company Name": "SBI Gold ETF", "Mkt Cap(Rs cr)": "206", "Last Price": "2693.85", "Change": "20.35", "link": "http://www.moneycontrol.com/india/stockpricequote/financeinvestments/sbimutualfundgoldexchangetradedscheme/SBI16"}, {"%Chg": "0.46", "Industry": "Finance - Investments", "Company Name": "IDBI Gold ETF", "Mkt Cap(Rs cr)": "89", "Last Price": "2659.15", "Change": "12.15", "link": "http://www.moneycontrol.com/india/stockpricequote/financeinvestments/idbigoldexchangetradedfund/IDB06"}, {"%Chg": "0.40", "Industry": "Finance - Investments", "Company Name": "Invesco India", "Mkt Cap(Rs cr)": "31", "Last Price": "2740.90", "Change": "10.90", "link": "http://www.moneycontrol.com/india/stockpricequote/financeinvestments/invescoindiagoldexchangetradedfund/RGE"}, {"%Chg": "0.36", "Industry": "Finance - Investments", "Company Name": "Birla Gold ETF", "Mkt Cap(Rs cr)": "63", "Last Price": "2775.00", "Change": "10.00", "link": "http://www.moneycontrol.com/india/stockpricequote/financeinvestments/birlasunlifegoldetf/BSL02"}, {"%Chg": "0.31", "Industry": "Finance - Investments", "Company Name": "HDFC Gold ETF", "Mkt Cap(Rs cr)": "418", "Last Price": "2716.50", "Change": "8.40", "link": "http://www.moneycontrol.com/india/stockpricequote/financeinvestments/hdfcmutualfundgoldexchangetradedfund/HDF02"}, {"%Chg": "0.09", "Industry": "Banks - Private Sector", "Company Name": "R Shares Gold ", "Mkt Cap(Rs cr)": "274", "Last Price": "2668.80", "Change": "2.50", "link": "http://www.moneycontrol.com/india/stockpricequote/banksprivatesector/rsharesgoldbees/GBE"}, {"%Chg": "-0.06", "Industry": "Banks - Public Sector", "Company Name": "UTI - Gold", "Mkt Cap(Rs cr)": "366", "Last Price": "2633.30", "Change": "-1.55", "link": "http://www.moneycontrol.com/india/stockpricequote/bankspublicsector/utigoldexchangetradedfund/UTI18"}, {"%Chg": "-0.27", "Industry": "Finance - Investments", "Company Name": "ICICI Gold ETF", "Mkt Cap(Rs cr)": "13", "Last Price": "275.95", "Change": "-0.75", "link": "http://www.moneycontrol.com/india/stockpricequote/financeinvestments/iciciprudentialgoldexchangetradedfund/ICI10"}]}